plotly_signif/__init__.py
plotly_signif/plotly_signif.py
plotly_signif-0.0.41.dist-info/LICENSE
plotly_signif-0.0.41.dist-info/METADATA
plotly_signif-0.0.41.dist-info/WHEEL
plotly_signif-0.0.41.dist-info/top_level.txt
plotly_signif-0.0.41.dist-info/RECORD
