Metadata-Version: 2.1
Name: plotly-signif
Version: 0.0.41
Summary: A python class of drawing a Bar/Box plot based on the plotly package, with freely definable statistical annotations
Home-page: https://github.com/sydddl/plotly-signif
Author: ZiChen Wang
Author-email: ZiChen Wang <2148519656@qq.com>
Classifier: Programming Language :: Python :: 3
Classifier: License :: OSI Approved :: MIT License
Requires-Python: >=3.7
License-File: LICENSE
